hac_intro2cs_tests-1.3.1.data/scripts/tests.py
inferno_tests/__init__.py
inferno_tests/tests.py
test_ex/__init__.py
test_ex/__main__.py
hac_intro2cs_tests-1.3.1.dist-info/LICENSE
hac_intro2cs_tests-1.3.1.dist-info/METADATA
hac_intro2cs_tests-1.3.1.dist-info/WHEEL
hac_intro2cs_tests-1.3.1.dist-info/entry_points.txt
hac_intro2cs_tests-1.3.1.dist-info/top_level.txt
hac_intro2cs_tests-1.3.1.dist-info/RECORD
