Metadata-Version: 2.1
Name: hac-intro2cs-tests
Version: 1.3.1
Summary: python tests for Hadassah Academic Collage intro2cs courses
Author: Hod Vaknin
License: MIT
Project-URL: Source, https://github.com/hodvak/inferno-tests
Platform: UNKNOWN
Classifier: Programming Language :: Python :: 3
License-File: LICENSE
